raw_bench/custom_stft.py
raw_bench/dataloader.py
raw_bench/logger.py
raw_bench/utils.py
raw_bench/attacks/__init__.py
raw_bench/attacks/compression.py
raw_bench/attacks/dynamics.py
raw_bench/attacks/filtering.py
raw_bench/attacks/low_level.py
raw_bench/attacks/neural_codecs.py
raw_bench/attacks/noise.py
raw_bench/attacks/reverb.py
raw_bench/attacks/specaugment.py
raw_bench/attacks/utils.py
raw_bench/model/__init__.py
raw_bench/model/silentcipher.py
raw_bench/solver/__init__.py
raw_bench/solver/audioseal.py
raw_bench/solver/base.py
raw_bench/solver/silentcipher.py
raw_bench/solver/wavmark.py
raw_bench-0.1.0.dist-info/licenses/LICENSE
runs/audioseal/eval/3sec/pretrained_on_strict_1/wandb/latest-run/files/code/scripts/eval.py
runs/audioseal/eval/3sec/pretrained_on_strict_1/wandb/run-20250602_180731-8ucboc3p/files/code/scripts/eval.py
runs/debugging/wandb/run-20250610_143423-5efcq6bj/files/code/scripts/eval.py
runs/timbre/debugging/wandb/latest-run/files/code/scripts/eval.py
runs/timbre/debugging/wandb/run-20250604_140756-akya6ysr/files/code/scripts/eval.py
runs/timbre/debugging/wandb/run-20250604_141615-3554cf1t/files/code/scripts/eval.py
runs/timbre/debugging/wandb/run-20250604_141934-i0wc54h1/files/code/scripts/eval.py
runs/timbre/debugging/wandb/run-20250604_142945-31x2ewey/files/code/scripts/eval.py
runs/timbre/debugging/wandb/run-20250604_143201-ejyb8j42/files/code/scripts/eval.py
runs/timbre/pretrained_on_strict/wandb/run-20250604_140448-s0vuajh8/files/code/scripts/eval.py
runs/timbre/pretrained_on_strict/wandb/run-20250604_140639-x2t8lmqb/files/code/scripts/eval.py
runs/wavmark/debugging/wandb/latest-run/files/code/scripts/eval.py
runs/wavmark/debugging/wandb/run-20250604_115558-zbcnfpye/files/code/scripts/eval.py
runs/wavmark/debugging/wandb/run-20250604_121858-1endl4n4/files/code/scripts/eval.py
runs/wavmark/debugging/wandb/run-20250604_122017-4zjg5lus/files/code/scripts/eval.py
runs/wavmark/debugging/wandb/run-20250604_122605-d48urbli/files/code/scripts/eval.py
raw_bench-0.1.0.dist-info/METADATA
raw_bench-0.1.0.dist-info/WHEEL
raw_bench-0.1.0.dist-info/top_level.txt
raw_bench-0.1.0.dist-info/RECORD
