Metadata-Version: 2.4
Name: raw-bench
Version: 0.1.0
Summary: A benchmarking suite for robust audio watermarking.
Author-email: Woosung Choi <Woosung.Choi@Sony.com>
Requires-Python: >=3.8
License-File: LICENSE
Requires-Dist: torch==2.1.0
Requires-Dist: torchaudio
Requires-Dist: torchinfo
Requires-Dist: torchinterp1d
Requires-Dist: audiomentations
Requires-Dist: descript-audio-codec
Requires-Dist: encodec
Requires-Dist: librosa==0.10.2
Requires-Dist: pysoundfile
Requires-Dist: grafx==0.6.0
Requires-Dist: audioseal
Requires-Dist: numpy
Requires-Dist: numba
Requires-Dist: pandas
Requires-Dist: scipy
Requires-Dist: einops
Requires-Dist: argbind
Requires-Dist: qqdm
Requires-Dist: hydra-core
Requires-Dist: tensorboard
Requires-Dist: tensorboardX
Requires-Dist: loguru
Requires-Dist: wandb
Requires-Dist: transformers
Requires-Dist: mel_cepstral_distance
Requires-Dist: kornia
Requires-Dist: torchlpc
Requires-Dist: wavmark
Dynamic: license-file
